{
  "symbol": "MQG.AX",
  "analysis_period_days": 14,
  "data_points": 227,
  "correlations": {
    "sentiment_vs_price": {
      "pearson": -0.2610650765710425,
      "pearson_p_value": 6.865995990905976e-05,
      "spearman": -0.3252482629617342,
      "spearman_p_value": 5.437439196557891e-07,
      "significance": "significant"
    },
    "sentiment_vs_volatility": {
      "pearson": -0.08838803116089333,
      "interpretation": "very_weak_negative"
    },
    "sentiment_vs_volume": {
      "pearson": -0.4691509553875457,
      "interpretation": "moderate_negative"
    },
    "lagged_correlations": {
      "1_day": -0.26493548618559914,
      "2_day": -0.25667298235518216,
      "3_day": -0.26291972451664797
    },
    "data_quality": {
      "total_points": 227,
      "valid_points": 227,
      "data_completeness": 1.0
    }
  },
  "event_impact": {
    "event_type_impacts": {},
    "summary": {
      "highest_impact_positive": null,
      "highest_impact_negative": null,
      "most_frequent_event": null,
      "average_impact": 0
    }
  },
  "predictive_metrics": {
    "prediction_accuracy": 0.6872246696035242,
    "confusion_matrix": {
      "positive_sentiment": {
        "up": 0,
        "down": 0,
        "flat": 10
      },
      "negative_sentiment": {
        "up": 0,
        "down": 0,
        "flat": 1
      },
      "neutral_sentiment": {
        "up": 54,
        "down": 6,
        "flat": 156
      }
    },
    "total_predictions": 227,
    "correct_predictions": 156,
    "sentiment_distribution": {
      "positive": 10,
      "negative": 1,
      "neutral": 216
    },
    "price_distribution": {
      "up": 54,
      "down": 6,
      "flat": 167
    }
  },
  "summary": "Sentiment-price correlation: -0.261 (significant). Weak correlation suggests other factors dominate price movements. ",
  "recommendations": [],
  "analysis_timestamp": "2025-09-04T22:17:51.373445",
  "analysis_version": "1.0"
}