{
  "symbol": "CBA.AX",
  "analysis_period_days": 14,
  "data_points": 114,
  "correlations": {
    "sentiment_vs_price": {
      "pearson": 0.37884554786993785,
      "pearson_p_value": 3.232867020273541e-05,
      "spearman": 0.345005566745613,
      "spearman_p_value": 0.00017048789561602084,
      "significance": "significant"
    },
    "sentiment_vs_volatility": {
      "pearson": -0.3329984256702509,
      "interpretation": "weak_negative"
    },
    "sentiment_vs_volume": {
      "pearson": -0.052571996318038355,
      "interpretation": "very_weak_negative"
    },
    "lagged_correlations": {
      "1_day": 0.39034382590682654,
      "2_day": 0.38876548389506727,
      "3_day": 0.38882651029833726
    },
    "data_quality": {
      "total_points": 114,
      "valid_points": 114,
      "data_completeness": 1.0
    }
  },
  "event_impact": {
    "event_type_impacts": {},
    "summary": {
      "highest_impact_positive": null,
      "highest_impact_negative": null,
      "most_frequent_event": null,
      "average_impact": 0
    }
  },
  "predictive_metrics": {
    "prediction_accuracy": 0.2894736842105263,
    "confusion_matrix": {
      "positive_sentiment": {
        "up": 0,
        "down": 0,
        "flat": 0
      },
      "negative_sentiment": {
        "up": 0,
        "down": 0,
        "flat": 0
      },
      "neutral_sentiment": {
        "up": 10,
        "down": 71,
        "flat": 33
      }
    },
    "total_predictions": 114,
    "correct_predictions": 33,
    "sentiment_distribution": {
      "positive": 0,
      "negative": 0,
      "neutral": 114
    },
    "price_distribution": {
      "up": 10,
      "down": 71,
      "flat": 33
    }
  },
  "summary": "Sentiment-price correlation: 0.379 (significant). Strong correlation suggests news sentiment is a good predictor. ",
  "recommendations": [],
  "analysis_timestamp": "2025-08-03T02:56:51.272844",
  "analysis_version": "1.0"
}